dash_mui/Button.py
dash_mui/DashMui.py
dash_mui/__init__.py
dash_mui/_imports_.py
dash_mui/async-DashMui.js
dash_mui/async-DashMui.js.map
dash_mui/dash_mui.min.js
dash_mui/dash_mui.min.js.map
dash_mui/metadata.json
dash_mui/package-info.json
dash_mui-0.0.1.dist-info/LICENSE
dash_mui-0.0.1.dist-info/METADATA
dash_mui-0.0.1.dist-info/WHEEL
dash_mui-0.0.1.dist-info/top_level.txt
dash_mui-0.0.1.dist-info/RECORD
